<?xml version="1.0"?>
<cutscene xmlns:xsi="http://www.w3.org/2001/XMLSchema-instance" xsi:noNamespaceSchemaLocation="cutscene.xsd">

  <director key="Terran Plot S2 C3"/>
  <environments>
    <environment_implicit name="marssector" sector="@playersector"/>
  </environments>
  <client menus="close">
    <input lock="all"/>
  </client>
  <presentation>
    <actions>
      <sequence name="MissionIntroCD" start="100">
        <shot name="shot1" environment="marssector" duration="8000">
          <camera_flyby distance="200" elevation="400" offset="400" reference="XenonScout" shaking="3" time="8000" interpolation="smooth" orient_to="object" overlay_texture="interlace" overlay_tile="1"/>
        </shot>
      </sequence>
    </actions>
  </presentation>
</cutscene>


