<?xml version="1.0" standalone="yes" ?>
<?xml-stylesheet href="x2script.xsl" type="text/xsl" ?>
<script>
<name>plugin.guilds.config.start</name>
<version>1</version>
<engineversion>63</engineversion>
<description>Guilds: Start config menu</description>
<arguments>
</arguments>
<sourceplaintext>
<![CDATA[
  START [PLAYERSHIP] ->open menu script: script=plugin.guilds.configmenu, value=null
  return null
]]>
</sourceplaintext>
<sourcetext>
<line indent=""><var>START&#160;</var><var>[PLAYERSHIP]&#160;-&gt;</var><text>open&#160;menu&#160;script:&#160;script=</text><call>plugin.guilds.configmenu</call><text>,&#160;value=</text><var>null</var></line>
<line indent=""><text>return&#160;</text><var>null</var></line>
</sourcetext>
<codearray>

<sval type="array" size="10">
  <sval type="string" val="plugin.guilds.config.start"/>
  <sval type="int" val="63"/>
  <sval type="string" val="Guilds: Start config menu"/>
  <sval type="int" val="1"/>
  <sval type="int" val="0"/>
  <sval type="int" val="0"/>
  <sval type="array" size="2">
    <sval type="array" size="7">
      <sval type="int" val="1700"/>
      <sval type="int" val="131075"/>
      <sval type="int" val="3"/>
      <sval type="int" val="-2147483646"/>
      <sval type="string" val="plugin.guilds.configmenu"/>
      <sval type="int" val="0"/>
      <sval type="int" val="0"/>
    </sval>
    <sval type="array" size="3">
      <sval type="int" val="103"/>
      <sval type="int" val="0"/>
      <sval type="int" val="0"/>
    </sval>
  </sval>
  <sval type="int" val="0"/>
  <sval type="int" val="0"/>
  <sval type="int" val="0"/>
</sval>

</codearray>
<nosignature>1273</nosignature>
</script>
